quaternions.py
quatpy-2025.1.1.dist-info/METADATA
quatpy-2025.1.1.dist-info/WHEEL
quatpy-2025.1.1.dist-info/licenses/LICENSE.txt
quatpy-2025.1.1.dist-info/RECORD
