Metadata-Version: 2.4
Name: quatpy
Version: 2025.1.1
Summary: A set of functions to manipulate quaternions.
Author-email: Jesse Charlton <57236497+jchar32@users.noreply.github.com>
License-File: LICENSE.txt
Classifier: Development Status :: 4 - Beta
Classifier: License :: OSI Approved :: MIT License
Classifier: Programming Language :: Python :: 3.12
Classifier: Topic :: Scientific/Engineering :: Mathematics
Requires-Python: >=3.12
Requires-Dist: numpy
